[
  {
    "uniqueId": "vaggelitsa.kol",
    "nickname": "𝒱𝒶𝑔𝑔𝑒𝓁𝒾𝓉𝓈𝒶 𝓀𝑜𝓁 🍓",
    "avatar": "https://p16-common-sign.tiktokcdn-us.com/tos-maliva-avt-0068/1233cbeefdd69252f0d32dd3858865fb~tplv-tiktokx-cropcenter:1080:1080.webp?dr=9640&refresh_token=39fb48cc&x-expires=1780934400&x-signature=GTHJOrfQzyEBEvofEKo2pWez7OM%3D&t=4d5b0474&ps=13740610&shp=a5d48078&shcp=fdd36af4&idc=useast5",
    "live_title": "",
    "start_time": 1780759717,
    "start_time_only_time": "18:28:37",
    "status": 2,
    "status_str": "Σε εξέλιξη",
    "stream_urls": {
      "hd": {
        "flv": "https://pull-flv-f77-tt04.tiktokcdn-us.com/stage/stream-1272426266148996417_hd5.flv?expire=1781975146&sign=a1fa681550fea945defe0d4ebea9c4c7"
      },
      "ao": {
        "flv": "https://pull-flv-f77-tt04.tiktokcdn-us.com/stage/stream-1272426266148996417.flv?expire=1781975146&sign=3d0cc13f850eec04917b212220fb1fcf&only_audio=1"
      },
      "ld": {
        "flv": "https://pull-flv-f77-tt04.tiktokcdn-us.com/stage/stream-1272426266148996417_ld5.flv?expire=1781975146&sign=4588dec0b510dd03605ea42bb271ddd0"
      },
      "sd": {
        "flv": "https://pull-flv-f77-tt04.tiktokcdn-us.com/stage/stream-1272426266148996417_zsd5.flv?expire=1781975146&sign=a8b716630c19130692ceb5232f509f0b"
      },
      "origin": {
        "flv": "https://pull-flv-f77-tt04.tiktokcdn-us.com/stage/stream-1272426266148996417.flv?expire=1781975146&sign=3d0cc13f850eec04917b212220fb1fcf"
      }
    }
  },
  {
    "uniqueId": "nataliakal21",
    "nickname": "Ναταλί♥️🦅",
    "avatar": "https://p19-common-sign.tiktokcdn-us.com/tos-maliva-avt-0068/22158800d7262da72112796e8ccf3732~tplv-tiktokx-cropcenter:1080:1080.webp?dr=9640&refresh_token=6284fae6&x-expires=1780934400&x-signature=HmokDxmaBn3JiDHOEOVsPH0414w%3D&t=4d5b0474&ps=13740610&shp=a5d48078&shcp=fdd36af4&idc=useast5",
    "live_title": "Χελοοουυ",
    "start_time": 1780762931,
    "start_time_only_time": "19:22:11",
    "status": 2,
    "status_str": "Σε εξέλιξη",
    "stream_urls": {
      "ld": {
        "flv": "https://pull-flv-f77-tt04.tiktokcdn-us.com/stage/stream-1272426481903469889_ld5.flv?expire=1781975181&sign=f3217a8273bf6ebb11cb4535eb54ce68"
      },
      "hd": {
        "flv": "https://pull-flv-f77-tt04.tiktokcdn-us.com/stage/stream-1272426481903469889_hd5.flv?expire=1781975181&sign=9d45389ecdfea2d39cd73401e285516e"
      },
      "ao": {
        "flv": "https://pull-flv-f77-tt04.tiktokcdn-us.com/stage/stream-1272426481903469889.flv?expire=1781975181&sign=093e0197eff968009139798a889b21bc&only_audio=1"
      },
      "sd": {
        "flv": "https://pull-flv-f77-tt04.tiktokcdn-us.com/stage/stream-1272426481903469889_zsd5.flv?expire=1781975181&sign=cbfeaffbd31880a132a74fe9c0b52929"
      },
      "origin": {
        "flv": "https://pull-flv-f77-tt04.tiktokcdn-us.com/stage/stream-1272426481903469889.flv?expire=1781975181&sign=093e0197eff968009139798a889b21bc"
      }
    }
  },
  {
    "uniqueId": "tzogk",
    "nickname": "TZOO🫶",
    "avatar": "https://p16-common-sign.tiktokcdn-us.com/tos-maliva-avt-0068/b01e0d28e7489a8b8a6db208dfecbe7a~tplv-tiktokx-cropcenter:1080:1080.webp?dr=9640&refresh_token=634b7499&x-expires=1780938000&x-signature=NbTVdHGiF82yBfcNk6ECmKLRed8%3D&t=4d5b0474&ps=13740610&shp=a5d48078&shcp=fdd36af4&idc=useast5",
    "live_title": "Καλώς ήρθες στο λαιβ μου❤️🫶🎼",
    "start_time": 1780751724,
    "start_time_only_time": "16:15:24",
    "status": 2,
    "status_str": "Σε εξέλιξη",
    "stream_urls": {
      "ld": {
        "flv": "https://pull-flv-f77-tt04.tiktokcdn-us.com/stage/stream-1272425729809712449_ld5.flv?expire=1781975206&sign=6ddadb63b3400bc8355124aa875fe37e"
      },
      "hd": {
        "flv": "https://pull-flv-f77-tt04.tiktokcdn-us.com/stage/stream-1272425729809712449_hd5.flv?expire=1781975206&sign=421b345bb433c23829b0d8213f3fe9a7"
      },
      "ao": {
        "flv": "https://pull-flv-f77-tt04.tiktokcdn-us.com/stage/stream-1272425729809712449.flv?expire=1781975206&sign=04a1580b354536a2ad9cefddfa541d7e&only_audio=1"
      },
      "sd": {
        "flv": "https://pull-flv-f77-tt04.tiktokcdn-us.com/stage/stream-1272425729809712449_zsd5.flv?expire=1781975206&sign=28f3f235c6c7e0d19f5b8289698cbc07"
      },
      "origin": {
        "flv": "https://pull-flv-f77-tt04.tiktokcdn-us.com/stage/stream-1272425729809712449.flv?expire=1781975206&sign=04a1580b354536a2ad9cefddfa541d7e"
      }
    }
  },
  {
    "uniqueId": "muglikat",
    "nickname": "Katerina MK🐈‍⬛",
    "avatar": "https://p16-common-sign.tiktokcdn-us.com/tos-maliva-avt-0068/3a9177d85b118eb959448f512575b274~tplv-tiktokx-cropcenter:1080:1080.webp?dr=9640&refresh_token=49a58e9c&x-expires=1780938000&x-signature=m%2Ba5H5eXSKJknjd3ovrLsKwMFWo%3D&t=4d5b0474&ps=13740610&shp=a5d48078&shcp=fdd36af4&idc=useast5",
    "live_title": "Καλωσορίσατε🤗￼ Привет 👋",
    "start_time": 1780764932,
    "start_time_only_time": "19:55:32",
    "status": 2,
    "status_str": "Σε εξέλιξη",
    "stream_urls": {
      "ld": {
        "flv": "https://pull-flv-f77-tt04.tiktokcdn-us.com/stage/stream-1272426616192763201_ld5.flv?expire=1781975222&sign=daf080c230f4c821ef0f934b8727bec1"
      },
      "hd": {
        "flv": "https://pull-flv-f77-tt04.tiktokcdn-us.com/stage/stream-1272426616192763201_hd5.flv?expire=1781975222&sign=864998ffbe351449ffb951403650833b"
      },
      "ao": {
        "flv": "https://pull-flv-f77-tt04.tiktokcdn-us.com/stage/stream-1272426616192763201.flv?expire=1781975222&sign=0bea935e9cadd8f7bca4edb2a0f287dc&only_audio=1"
      },
      "origin": {
        "flv": "https://pull-flv-f77-tt04.tiktokcdn-us.com/stage/stream-1272426616192763201.flv?expire=1781975222&sign=0bea935e9cadd8f7bca4edb2a0f287dc"
      },
      "sd": {
        "flv": "https://pull-flv-f77-tt04.tiktokcdn-us.com/stage/stream-1272426616192763201_zsd5.flv?expire=1781975222&sign=ac521a8547412e7578683a6a5476f7e1"
      }
    }
  },
  {
    "uniqueId": "michalis_evripiotis",
    "nickname": "Michalis Evripiotis🏝️",
    "avatar": "https://p16-common-sign.tiktokcdn-us.com/tos-maliva-avt-0068/b474eacf5f06d910eafef31f2a7d43ef~tplv-tiktokx-cropcenter:1080:1080.webp?dr=9640&refresh_token=a7739ca9&x-expires=1780938000&x-signature=jiR9zo8VicsknplV5cCUL3jCzjc%3D&t=4d5b0474&ps=13740610&shp=a5d48078&shcp=fdd36af4&idc=useast5",
    "live_title": "Λωλαθηκαμε 🏝️",
    "start_time": 1780765261,
    "start_time_only_time": "20:01:01",
    "status": 2,
    "status_str": "Σε εξέλιξη",
    "stream_urls": {
      "ld": {
        "flv": "https://pull-flv-f77-tt04.tiktokcdn-us.com/stage/stream-1272426638256637249_ld5.flv?expire=1781975227&sign=2a78c9c7b0828a55f81a1718abbdb694"
      },
      "hd": {
        "flv": "https://pull-flv-f77-tt04.tiktokcdn-us.com/stage/stream-1272426638256637249_hd5.flv?expire=1781975227&sign=5c12f7cade7179bf5a8acffc797071df"
      },
      "ao": {
        "flv": "https://pull-flv-f77-tt04.tiktokcdn-us.com/stage/stream-1272426638256637249.flv?expire=1781975227&sign=bec06953d3161a591402b44cfde1ed1b&only_audio=1"
      },
      "sd": {
        "flv": "https://pull-flv-f77-tt04.tiktokcdn-us.com/stage/stream-1272426638256637249_zsd5.flv?expire=1781975227&sign=5eb072ad8efa3e5a732a0aeb7b5ca38a"
      },
      "origin": {
        "flv": "https://pull-flv-f77-tt04.tiktokcdn-us.com/stage/stream-1272426638256637249.flv?expire=1781975227&sign=bec06953d3161a591402b44cfde1ed1b"
      }
    }
  },
  {
    "uniqueId": "dimnicklive",
    "nickname": "Dim&Nick Live",
    "avatar": "https://p19-common-sign.tiktokcdn-us.com/tos-maliva-avt-0068/0cf101ec21cf2fd1817cb44421e77b85~tplv-tiktokx-cropcenter:1080:1080.webp?dr=9640&refresh_token=5c2bcd8d&x-expires=1780938000&x-signature=rglNorF2%2BQkrIvC8AaEAOoV%2BrIs%3D&t=4d5b0474&ps=13740610&shp=a5d48078&shcp=fdd36af4&idc=useast5",
    "live_title": "Road to D5!",
    "start_time": 1780758698,
    "start_time_only_time": "18:11:38",
    "status": 2,
    "status_str": "Σε εξέλιξη",
    "stream_urls": {
      "hd": {
        "flv": "https://pull-flv-f77-tt04.tiktokcdn-us.com/stage/stream-1272426197825619265_hd5.flv?expire=1781975232&sign=03de105739d8a4eb00b10cd0f25f3a95"
      },
      "ao": {
        "flv": "https://pull-flv-f77-tt04.tiktokcdn-us.com/stage/stream-1272426197825619265.flv?expire=1781975232&sign=e9dc97f1754d85fc5d883b180fe2a43f&only_audio=1"
      },
      "ld": {
        "flv": "https://pull-flv-f77-tt04.tiktokcdn-us.com/stage/stream-1272426197825619265_ld5.flv?expire=1781975232&sign=e5d159c7ddb5b6ccaad23535cda658af"
      },
      "sd": {
        "flv": "https://pull-flv-f77-tt04.tiktokcdn-us.com/stage/stream-1272426197825619265_zsd5.flv?expire=1781975232&sign=e1c5baee542bb2ddd6482f7994f24aca"
      },
      "origin": {
        "flv": "https://pull-flv-f77-tt04.tiktokcdn-us.com/stage/stream-1272426197825619265.flv?expire=1781975232&sign=e9dc97f1754d85fc5d883b180fe2a43f"
      }
    }
  },
  {
    "uniqueId": "kwnstantina_pk",
    "nickname": "💥𝓚𝔀𝓷𝓼𝓽𝓪𝓷𝓽𝓲𝓷𝓪💥",
    "avatar": "https://p16-common-sign.tiktokcdn-us.com/tos-maliva-avt-0068/db549b519e8ef07c916d80be4d08ad81~tplv-tiktokx-cropcenter:1080:1080.webp?dr=9640&refresh_token=41388cd7&x-expires=1780938000&x-signature=OgrfziwY9x6uodhR84sNfMgv5N4%3D&t=4d5b0474&ps=13740610&shp=a5d48078&shcp=fdd36af4&idc=useast5",
    "live_title": "💥💥💥💥",
    "start_time": 1780757537,
    "start_time_only_time": "17:52:17",
    "status": 2,
    "status_str": "Σε εξέλιξη",
    "stream_urls": {
      "ao": {
        "flv": "https://pull-flv-f77-tt04.tiktokcdn-us.com/stage/stream-1272426119909868865.flv?expire=1781975239&sign=6a9a2e7c8467b142aec987d2bf21e75c&only_audio=1"
      },
      "ld": {
        "flv": "https://pull-flv-f77-tt04.tiktokcdn-us.com/stage/stream-1272426119909868865_ld5.flv?expire=1781975239&sign=a4f4f2ec57fd54cdea8f7284f96acda6"
      },
      "hd": {
        "flv": "https://pull-flv-f77-tt04.tiktokcdn-us.com/stage/stream-1272426119909868865_hd5.flv?expire=1781975239&sign=558e8f41968e363974e2821c90e693f4"
      },
      "origin": {
        "flv": "https://pull-flv-f77-tt04.tiktokcdn-us.com/stage/stream-1272426119909868865.flv?expire=1781975239&sign=6a9a2e7c8467b142aec987d2bf21e75c"
      },
      "sd": {
        "flv": "https://pull-flv-f77-tt04.tiktokcdn-us.com/stage/stream-1272426119909868865_zsd5.flv?expire=1781975239&sign=051c9a6f5907c3893802196602728d89"
      }
    }
  },
  {
    "uniqueId": "lemeirini",
    "nickname": "loumouuu🪬🪽",
    "avatar": "https://p16-common-sign.tiktokcdn-us.com/tos-maliva-avt-0068/edc41dcbc6c2bb5ca52e1994b9584060~tplv-tiktokx-cropcenter:1080:1080.webp?dr=9640&refresh_token=827907a7&x-expires=1780938000&x-signature=5TRJt3lMtlyWhebrnisc%2FXaK38o%3D&t=4d5b0474&ps=13740610&shp=a5d48078&shcp=fdd36af4&idc=useast5",
    "live_title": "παμε λιγοοο💦",
    "start_time": 1780764462,
    "start_time_only_time": "19:47:42",
    "status": 2,
    "status_str": "Σε εξέλιξη",
    "stream_urls": {
      "ld": {
        "flv": "https://pull-flv-f77-tt04.tiktokcdn-us.com/stage/stream-1272426584705598785_ld5.flv?expire=1781975244&sign=a01af0eb60bb8cb674bcc4a2ac0451e4"
      },
      "hd": {
        "flv": "https://pull-flv-f77-tt04.tiktokcdn-us.com/stage/stream-1272426584705598785_hd5.flv?expire=1781975244&sign=993d1001067f335b411e550055a82eac"
      },
      "ao": {
        "flv": "https://pull-flv-f77-tt04.tiktokcdn-us.com/stage/stream-1272426584705598785.flv?expire=1781975244&sign=07cf9504af77108e55315983183641f8&only_audio=1"
      },
      "sd": {
        "flv": "https://pull-flv-f77-tt04.tiktokcdn-us.com/stage/stream-1272426584705598785_zsd5.flv?expire=1781975244&sign=d322e40ac59650fc2f0d7194ad2ea7e4"
      },
      "origin": {
        "flv": "https://pull-flv-f77-tt04.tiktokcdn-us.com/stage/stream-1272426584705598785.flv?expire=1781975244&sign=07cf9504af77108e55315983183641f8"
      }
    }
  },
  {
    "uniqueId": "pinarkrlii",
    "nickname": "pinarkrli",
    "avatar": "https://p16-common-sign.tiktokcdn-us.com/tos-maliva-avt-0068/06362d2e50d4e0713683cea003b1a685~tplv-tiktokx-cropcenter:1080:1080.webp?dr=9640&refresh_token=eee1135a&x-expires=1780934400&x-signature=ei7TuqjAWWtVQzPFTWOgvUuEi%2B8%3D&t=4d5b0474&ps=13740610&shp=a5d48078&shcp=fdd36af4&idc=useast5",
    "live_title": "",
    "start_time": 1780761146,
    "start_time_only_time": "18:52:26",
    "status": 2,
    "status_str": "Σε εξέλιξη",
    "stream_urls": {
      "hd": {
        "flv": "https://pull-flv-f77-tt04.tiktokcdn-us.com/stage/stream-1272426362171032897_hd5.flv?expire=1781975274&sign=c24c50c1bc02c18c9ce8ccd7ae01b158"
      },
      "ao": {
        "flv": "https://pull-flv-f77-tt04.tiktokcdn-us.com/stage/stream-1272426362171032897.flv?expire=1781975274&sign=8fa81d7072c561938ed9b6950393b598&only_audio=1"
      },
      "ld": {
        "flv": "https://pull-flv-f77-tt04.tiktokcdn-us.com/stage/stream-1272426362171032897_ld5.flv?expire=1781975274&sign=46a4c1756852390fc06b6f593dd3853b"
      },
      "sd": {
        "flv": "https://pull-flv-f77-tt04.tiktokcdn-us.com/stage/stream-1272426362171032897_zsd5.flv?expire=1781975274&sign=019cb6ac58286d926677cf7d803b3cb2"
      },
      "origin": {
        "flv": "https://pull-flv-f77-tt04.tiktokcdn-us.com/stage/stream-1272426362171032897.flv?expire=1781975274&sign=8fa81d7072c561938ed9b6950393b598"
      }
    }
  },
  {
    "uniqueId": "chris.fintr",
    "nickname": "𝑪𝑯𝑹𝑰𝑺! Σιωπή 🤫=Χρυσός🥇",
    "avatar": "https://p16-common-sign.tiktokcdn-us.com/tos-maliva-avt-0068/6f70d8525c3390d0a57085abaa729c7c~tplv-tiktokx-cropcenter:1080:1080.webp?dr=9640&refresh_token=8a7aaebb&x-expires=1780934400&x-signature=S7WGaSmhUERElCsHfSvhuU6KyG4%3D&t=4d5b0474&ps=13740610&shp=a5d48078&shcp=fdd36af4&idc=useast5",
    "live_title": "",
    "start_time": 1780750525,
    "start_time_only_time": "15:55:25",
    "status": 2,
    "status_str": "Σε εξέλιξη",
    "stream_urls": {
      "ld": {
        "flv": "https://pull-flv-l77-tt04.tiktokcdn-us.com/stage/stream-1272425649275405909_ld5.flv?expire=1781975297&sign=3471d9d573b059f7f1dcb1532887070b"
      },
      "hd": {
        "flv": "https://pull-flv-l77-tt04.tiktokcdn-us.com/stage/stream-1272425649275405909_hd5.flv?expire=1781975297&sign=98e52affa0184644935de8c76a434111"
      },
      "ao": {
        "flv": "https://pull-flv-l77-tt04.tiktokcdn-us.com/stage/stream-1272425649275405909.flv?expire=1781975297&sign=0012c62e9027eddf9ee386ae86c22944&only_audio=1"
      },
      "origin": {
        "flv": "https://pull-flv-l77-tt04.tiktokcdn-us.com/stage/stream-1272425649275405909.flv?expire=1781975297&sign=0012c62e9027eddf9ee386ae86c22944"
      },
      "sd": {
        "flv": "https://pull-flv-l77-tt04.tiktokcdn-us.com/stage/stream-1272425649275405909_zsd5.flv?expire=1781975297&sign=66ad18ad52146bcbd9bbb34605110936"
      }
    }
  },
  {
    "uniqueId": "petrostsernios",
    "nickname": "tsernios Petros",
    "avatar": "https://p16-common-sign.tiktokcdn-us.com/tos-maliva-avt-0068/2ceff407f2c6a1468cf56e003cd0f388~tplv-tiktokx-cropcenter:1080:1080.webp?dr=9640&refresh_token=fb4b32c8&x-expires=1780938000&x-signature=fFSgtz7zshL86Xq0pP6RbUNIqjo%3D&t=4d5b0474&ps=13740610&shp=a5d48078&shcp=fdd36af4&idc=useast5",
    "live_title": "ανακατεύουμε τα βοσκοτόπια",
    "start_time": 1780761086,
    "start_time_only_time": "18:51:26",
    "status": 2,
    "status_str": "Σε εξέλιξη",
    "stream_urls": {
      "hd": {
        "flv": "https://pull-flv-f77-tt04.tiktokcdn-us.com/stage/stream-1272426358091285825_hd5.flv?expire=1781975315&sign=63ae4766500197eb4ab9cc99d9379a03"
      },
      "ao": {
        "flv": "https://pull-flv-f77-tt04.tiktokcdn-us.com/stage/stream-1272426358091285825.flv?expire=1781975315&sign=0cf250ff4edddb11b0fb1727d6ac8d8e&only_audio=1"
      },
      "ld": {
        "flv": "https://pull-flv-f77-tt04.tiktokcdn-us.com/stage/stream-1272426358091285825_ld5.flv?expire=1781975315&sign=8262c75d582178cbad81123893f3702b"
      },
      "origin": {
        "flv": "https://pull-flv-f77-tt04.tiktokcdn-us.com/stage/stream-1272426358091285825.flv?expire=1781975315&sign=0cf250ff4edddb11b0fb1727d6ac8d8e"
      },
      "sd": {
        "flv": "https://pull-flv-f77-tt04.tiktokcdn-us.com/stage/stream-1272426358091285825_zsd5.flv?expire=1781975315&sign=e6b6751f2257f8b74516d4948b44f909"
      }
    }
  }
]