[
  {
    "uniqueId": "dwroula0",
    "nickname": "Dwroula0🫧",
    "avatar": "https://p16-common-sign.tiktokcdn-us.com/tos-maliva-avt-0068/d858c98473fa90aeaa4f69b72c7f7282~tplv-tiktokx-cropcenter:1080:1080.webp?dr=9640&refresh_token=e58ce249&x-expires=1783080000&x-signature=SSR3KWTT%2FhQ4gl6AtScu4ZOxt70%3D&t=4d5b0474&ps=13740610&shp=a5d48078&shcp=fdd36af4&idc=useast5",
    "live_title": "",
    "start_time": 1782908584,
    "start_time_only_time": "15:23:04",
    "status": 2,
    "status_str": "Σε εξέλιξη",
    "stream_urls": {
      "ao": {
        "flv": "https://pull-flv-f77-tt04.tiktokcdn-us.com/stage/stream-1272570474164127041.flv?expire=1784118683&sign=3a32322371654c369546d843c1a3cc4e&only_audio=1"
      },
      "ld": {
        "flv": "https://pull-flv-f77-tt04.tiktokcdn-us.com/stage/stream-1272570474164127041_ld5.flv?expire=1784118683&sign=070fdac38bb73c10dbe6e862fe527bfd"
      },
      "hd": {
        "flv": "https://pull-flv-f77-tt04.tiktokcdn-us.com/stage/stream-1272570474164127041_hd5.flv?expire=1784118683&sign=5d2e22aa395ff177ad4cba52d92c8b1a"
      },
      "sd": {
        "flv": "https://pull-flv-f77-tt04.tiktokcdn-us.com/stage/stream-1272570474164127041_zsd5.flv?expire=1784118683&sign=226b087619c082ffaa17b3be6c173a72"
      },
      "origin": {
        "flv": "https://pull-flv-f77-tt04.tiktokcdn-us.com/stage/stream-1272570474164127041.flv?expire=1784118683&sign=3a32322371654c369546d843c1a3cc4e"
      }
    }
  },
  {
    "uniqueId": "chris.fintr",
    "nickname": "𝑪𝑯𝑹𝑰𝑺! Σιωπή 🤫=Χρυσός🥇",
    "avatar": "https://p16-common-sign.tiktokcdn-us.com/tos-maliva-avt-0068/50543760f46bca7134786ccd19c48816~tplv-tiktokx-cropcenter:1080:1080.webp?dr=9640&refresh_token=2d305930&x-expires=1783076400&x-signature=4NQtIsXEktxaAzhhdLQXBAxuoCo%3D&t=4d5b0474&ps=13740610&shp=a5d48078&shcp=fdd36af4&idc=useast5",
    "live_title": "",
    "start_time": 1782905048,
    "start_time_only_time": "14:24:08",
    "status": 2,
    "status_str": "Σε εξέλιξη",
    "stream_urls": {
      "hd": {
        "flv": "https://pull-flv-l77-tt04.tiktokcdn-us.com/stage/stream-1272570236931933781_hd5.flv?expire=1784118811&sign=8a2a0da7e9fb1987513e6164659a80d2"
      },
      "ao": {
        "flv": "https://pull-flv-l77-tt04.tiktokcdn-us.com/stage/stream-1272570236931933781.flv?expire=1784118811&sign=ddb92245e6695a6d10f3d5d28e75a13f&only_audio=1"
      },
      "ld": {
        "flv": "https://pull-flv-l77-tt04.tiktokcdn-us.com/stage/stream-1272570236931933781_ld5.flv?expire=1784118811&sign=e4f7bd2ec811afb8e9f1a3ae178a4758"
      },
      "origin": {
        "flv": "https://pull-flv-l77-tt04.tiktokcdn-us.com/stage/stream-1272570236931933781.flv?expire=1784118811&sign=ddb92245e6695a6d10f3d5d28e75a13f"
      },
      "sd": {
        "flv": "https://pull-flv-l77-tt04.tiktokcdn-us.com/stage/stream-1272570236931933781_zsd5.flv?expire=1784118811&sign=457b022fdb00b63c407037f6b9ca3e71"
      }
    }
  },
  {
    "uniqueId": "giannelis_",
    "nickname": "Giannelis",
    "avatar": "https://p19-common-sign.tiktokcdn-us.com/tos-useast2a-avt-0068-euttp/c10dd8f50ee9745c47fb0a61cd723df8~tplv-tiktokx-cropcenter:1080:1080.webp?dr=9640&refresh_token=673c8245&x-expires=1783080000&x-signature=gr0vbCw4D1UFwy3jaJENVE4zvw0%3D&t=4d5b0474&ps=13740610&shp=a5d48078&shcp=fdd36af4&idc=useast5",
    "live_title": "Γεια",
    "start_time": 1782907731,
    "start_time_only_time": "15:08:51",
    "status": 2,
    "status_str": "Σε εξέλιξη",
    "stream_urls": {
      "ld": {
        "flv": "https://pull-flv-l77-tt04.tiktokcdn-us.com/stage/stream-1272570416989472341_ld5.flv?expire=1784118844&sign=cad80488ddac4c72ff31f731a476a949"
      },
      "hd": {
        "flv": "https://pull-flv-l77-tt04.tiktokcdn-us.com/stage/stream-1272570416989472341_hd5.flv?expire=1784118844&sign=bde259c2dae30be1351731445c8adaa6"
      },
      "ao": {
        "flv": "https://pull-flv-l77-tt04.tiktokcdn-us.com/stage/stream-1272570416989472341.flv?expire=1784118844&sign=68d24c166e3f71c1a0bd15a2f288552c&only_audio=1"
      },
      "sd": {
        "flv": "https://pull-flv-l77-tt04.tiktokcdn-us.com/stage/stream-1272570416989472341_zsd5.flv?expire=1784118844&sign=effff3c9a899c09ff58e98d806867c4d"
      },
      "origin": {
        "flv": "https://pull-flv-l77-tt04.tiktokcdn-us.com/stage/stream-1272570416989472341.flv?expire=1784118844&sign=68d24c166e3f71c1a0bd15a2f288552c"
      }
    }
  }
]