[
  {
    "uniqueId": "aurhlios1",
    "nickname": "ΘΕΊΑ ΑΥΡΙΛΙΟΣ",
    "avatar": "https://p19-common-sign.tiktokcdn-us.com/tos-maliva-avt-0068/1baa069b3c5e493391f7d66359166382~tplv-tiktokx-cropcenter:1080:1080.webp?dr=9640&refresh_token=5f6290ad&x-expires=1771624800&x-signature=IAe9tC2IZfOzbE4P7g5tBCvCq1w%3D&t=4d5b0474&ps=13740610&shp=a5d48078&shcp=fdd36af4&idc=useast8",
    "live_title": "",
    "start_time": 1771446961,
    "start_time_only_time": "22:36:01",
    "status": 2,
    "status_str": "Σε εξέλιξη",
    "stream_urls": {
      "ld": {
        "flv": "https://pull-flv-l77-tt04.tiktokcdn-us.com/stage/stream-1271801297750459989_ld5.flv?expire=1772665543&sign=2a4368aea9c8b24710ab59714aada697"
      },
      "hd": {
        "flv": "https://pull-flv-l77-tt04.tiktokcdn-us.com/stage/stream-1271801297750459989_hd5.flv?expire=1772665543&sign=424f0070539e9d06b2dca1b76c7d6a62"
      },
      "ao": {
        "flv": "https://pull-flv-l77-tt04.tiktokcdn-us.com/stage/stream-1271801297750459989.flv?expire=1772665543&sign=0065c0d6f81b71c4780f8defd6c8cf2e&only_audio=1"
      },
      "origin": {
        "flv": "https://pull-flv-l77-tt04.tiktokcdn-us.com/stage/stream-1271801297750459989.flv?expire=1772665543&sign=0065c0d6f81b71c4780f8defd6c8cf2e"
      },
      "sd": {
        "flv": "https://pull-flv-l77-tt04.tiktokcdn-us.com/stage/stream-1271801297750459989_zsd5.flv?expire=1772665543&sign=aa3112412c21bb9958df2c08b71d5944"
      }
    }
  },
  {
    "uniqueId": "ngradiogr",
    "nickname": "NGradio.gr",
    "avatar": "https://p16-common-sign.tiktokcdn-us.com/tos-maliva-avt-0068/a76c84f76a1baec2f6f809cdd73a8023~tplv-tiktokx-cropcenter:1080:1080.webp?dr=9640&refresh_token=251212df&x-expires=1771628400&x-signature=tBC7GOzusLuqFeiXkw%2FDqN%2BbMt0%3D&t=4d5b0474&ps=13740610&shp=a5d48078&shcp=fdd36af4&idc=useast8",
    "live_title": "",
    "start_time": 1771455735,
    "start_time_only_time": "01:02:15",
    "status": 2,
    "status_str": "Σε εξέλιξη",
    "stream_urls": {
      "origin": {
        "flv": "https://pull-flv-f77-tt04.tiktokcdn-us.com/stage/stream-1271801886612915521.flv?expire=1772665563&sign=c2a3162687288da6145c9e7d140a0475"
      },
      "sd": {
        "flv": "https://pull-flv-f77-tt04.tiktokcdn-us.com/stage/stream-1271801886612915521_zsd5.flv?expire=1772665563&sign=c36a3996adbfe4d6688a3f934d8e5c0c"
      },
      "ld": {
        "flv": "https://pull-flv-f77-tt04.tiktokcdn-us.com/stage/stream-1271801886612915521_ld5.flv?expire=1772665563&sign=1b5800ec614d38cf6906309819e88df5"
      },
      "hd": {
        "flv": "https://pull-flv-f77-tt04.tiktokcdn-us.com/stage/stream-1271801886612915521_hd5.flv?expire=1772665563&sign=9ed40848e51910cbad3b2cf62c2ca679"
      },
      "ao": {
        "flv": "https://pull-flv-f77-tt04.tiktokcdn-us.com/stage/stream-1271801886612915521.flv?expire=1772665563&sign=c2a3162687288da6145c9e7d140a0475&only_audio=1"
      }
    }
  },
  {
    "uniqueId": "linamistiliadou",
    "nickname": "L i n a M i s t i l i a d u ™️",
    "avatar": "https://p19-common-sign.tiktokcdn-us.com/tos-maliva-avt-0068/0663edf04a0059b6d2609f09f958a727~tplv-tiktokx-cropcenter:1080:1080.webp?dr=9640&refresh_token=3d676163&x-expires=1771628400&x-signature=AvE5FRMKs21BnFoHZst9%2F6oXzIc%3D&t=4d5b0474&ps=13740610&shp=a5d48078&shcp=fdd36af4&idc=useast8",
    "live_title": "Jack Sparra 🏴‍☠️",
    "start_time": 1771441311,
    "start_time_only_time": "21:01:51",
    "status": 2,
    "status_str": "Σε εξέλιξη",
    "stream_urls": {
      "origin": {
        "flv": "https://pull-flv-l77-tt04.tiktokcdn-us.com/stage/stream-1271800918631777877.flv?expire=1772665569&sign=a44cadcae2fa11c6501cce8ca9926b0a"
      },
      "sd": {
        "flv": "https://pull-flv-l77-tt04.tiktokcdn-us.com/stage/stream-1271800918631777877_zsd5.flv?expire=1772665569&sign=089e6b88903531eb06ffac470586b8fe"
      },
      "ld": {
        "flv": "https://pull-flv-l77-tt04.tiktokcdn-us.com/stage/stream-1271800918631777877_ld5.flv?expire=1772665569&sign=e369ac9c4899f01c1c2a821b296546e3"
      },
      "hd": {
        "flv": "https://pull-flv-l77-tt04.tiktokcdn-us.com/stage/stream-1271800918631777877_hd5.flv?expire=1772665569&sign=185875bbbf85cc04c37c344052c31d6f"
      },
      "ao": {
        "flv": "https://pull-flv-l77-tt04.tiktokcdn-us.com/stage/stream-1271800918631777877.flv?expire=1772665569&sign=a44cadcae2fa11c6501cce8ca9926b0a&only_audio=1"
      }
    }
  },
  {
    "uniqueId": "grintelas.com",
    "nickname": "GRINTELAS.com",
    "avatar": "https://p16-common-sign.tiktokcdn-us.com/tos-useast2a-avt-0068-euttp/321e6c869564c37b0c0f2b91062cd91c~tplv-tiktokx-cropcenter:1080:1080.webp?dr=9640&refresh_token=70ff3a1b&x-expires=1771624800&x-signature=MPYXDo0lQWaYESPugikB76pDIlU%3D&t=4d5b0474&ps=13740610&shp=a5d48078&shcp=fdd36af4&idc=useast8",
    "live_title": "",
    "start_time": 1771450932,
    "start_time_only_time": "23:42:12",
    "status": 2,
    "status_str": "Σε εξέλιξη",
    "stream_urls": {
      "ao": {
        "flv": "https://pull-flv-l77-tt04.tiktokcdn-us.com/stage/stream-1271801564237661781.flv?expire=1772665572&sign=982b2329826e9aefb6b8e0814f309b3a&only_audio=1"
      },
      "origin": {
        "flv": "https://pull-flv-l77-tt04.tiktokcdn-us.com/stage/stream-1271801564237661781.flv?expire=1772665572&sign=982b2329826e9aefb6b8e0814f309b3a"
      },
      "sd": {
        "flv": "https://pull-flv-l77-tt04.tiktokcdn-us.com/stage/stream-1271801564237661781_zsd5.flv?expire=1772665572&sign=eaba31d431cb08c7b31478f4e8047000"
      },
      "ld": {
        "flv": "https://pull-flv-l77-tt04.tiktokcdn-us.com/stage/stream-1271801564237661781_ld5.flv?expire=1772665572&sign=490521657b6b5c9435b0bda8766a0045"
      },
      "hd": {
        "flv": "https://pull-flv-l77-tt04.tiktokcdn-us.com/stage/stream-1271801564237661781_hd5.flv?expire=1772665572&sign=d3e085a46828904e91eed6dafc838b28"
      }
    }
  },
  {
    "uniqueId": "alexandravahtanidou",
    "nickname": "🏴‍☠️ ѦȽⵟⵋѦƝⵠⴽѦ 🏴‍☠️",
    "avatar": "https://p16-common-sign.tiktokcdn-us.com/tos-maliva-avt-0068/1d0af0b60200edec0c9ab3ff8a255d37~tplv-tiktokx-cropcenter:1080:1080.webp?dr=9640&refresh_token=b1bfa2af&x-expires=1771628400&x-signature=Wy93Kte2Kucr4iAayVf2CxxITps%3D&t=4d5b0474&ps=13740610&shp=a5d48078&shcp=fdd36af4&idc=useast8",
    "live_title": "Let’s have fun🤩",
    "start_time": 1771439067,
    "start_time_only_time": "20:24:27",
    "status": 2,
    "status_str": "Σε εξέλιξη",
    "stream_urls": {
      "origin": {
        "flv": "https://pull-flv-l77-tt04.tiktokcdn-us.com/stage/stream-1271800768057312853.flv?expire=1772665608&sign=c6fcbc11f3b30308890a67cdc941d8e4"
      },
      "sd": {
        "flv": "https://pull-flv-l77-tt04.tiktokcdn-us.com/stage/stream-1271800768057312853_zsd5.flv?expire=1772665608&sign=304f0e168c9198c3dbae1fabbb23baea"
      },
      "ld": {
        "flv": "https://pull-flv-l77-tt04.tiktokcdn-us.com/stage/stream-1271800768057312853_ld5.flv?expire=1772665608&sign=4e5ffe38f08195d88c3f515d50b05332"
      },
      "ao": {
        "flv": "https://pull-flv-l77-tt04.tiktokcdn-us.com/stage/stream-1271800768057312853.flv?expire=1772665608&sign=c6fcbc11f3b30308890a67cdc941d8e4&only_audio=1"
      }
    }
  },
  {
    "uniqueId": "efeli_giaki",
    "nickname": "Efeli🐉",
    "avatar": "https://p16-common-sign.tiktokcdn-us.com/tos-maliva-avt-0068/15b924b7f642dd0a1391438d4eaba1df~tplv-tiktokx-cropcenter:1080:1080.webp?dr=9640&refresh_token=4069a6d1&x-expires=1771628400&x-signature=00w01Fq%2FB0ipKp0JpMx%2B1ES1%2Flk%3D&t=4d5b0474&ps=13740610&shp=a5d48078&shcp=fdd36af4&idc=useast8",
    "live_title": "Eiiii❤️",
    "start_time": 1771446477,
    "start_time_only_time": "22:27:57",
    "status": 2,
    "status_str": "Σε εξέλιξη",
    "stream_urls": {
      "ld": {
        "flv": "https://pull-flv-f77-tt04.tiktokcdn-us.com/stage/stream-1271801265269245249_ld5.flv?expire=1772665613&sign=4c5bc126f30544de60f5dca8f30ac2d2"
      },
      "hd": {
        "flv": "https://pull-flv-f77-tt04.tiktokcdn-us.com/stage/stream-1271801265269245249_hd5.flv?expire=1772665613&sign=e17317f0d6c3954fc8a36e58e333ff6f"
      },
      "ao": {
        "flv": "https://pull-flv-f77-tt04.tiktokcdn-us.com/stage/stream-1271801265269245249.flv?expire=1772665613&sign=578efc538694b2f59c795d9cda5c9d40&only_audio=1"
      },
      "origin": {
        "flv": "https://pull-flv-f77-tt04.tiktokcdn-us.com/stage/stream-1271801265269245249.flv?expire=1772665613&sign=578efc538694b2f59c795d9cda5c9d40"
      },
      "sd": {
        "flv": "https://pull-flv-f77-tt04.tiktokcdn-us.com/stage/stream-1271801265269245249_zsd5.flv?expire=1772665613&sign=5d8d817c3bca20619e0c18d03f6f1f20"
      }
    }
  },
  {
    "uniqueId": "_alex.lou_",
    "nickname": "Aleksandros",
    "avatar": "https://p16-common-sign.tiktokcdn-us.com/tos-maliva-avt-0068/da538670be0c035bf0648659311caf17~tplv-tiktokx-cropcenter:1080:1080.webp?dr=9640&refresh_token=a89212c0&x-expires=1771624800&x-signature=Lsaelly7cdlgulIEGUq9i%2F5CBfA%3D&t=4d5b0474&ps=13740610&shp=a5d48078&shcp=fdd36af4&idc=useast8",
    "live_title": "Aleksandros on top 🚀",
    "start_time": 1771449332,
    "start_time_only_time": "23:15:32",
    "status": 2,
    "status_str": "Σε εξέλιξη",
    "stream_urls": {
      "origin": {
        "flv": "https://pull-flv-l77-tt04.tiktokcdn-us.com/stage/stream-1271801456865052245.flv?expire=1772665620&sign=4b6b9a6477346eb96f69dda01ea81501"
      },
      "sd": {
        "flv": "https://pull-flv-l77-tt04.tiktokcdn-us.com/stage/stream-1271801456865052245_zsd5.flv?expire=1772665620&sign=978fee7e45f2ac35a4a5cbbbf9b1e9dc"
      },
      "ld": {
        "flv": "https://pull-flv-l77-tt04.tiktokcdn-us.com/stage/stream-1271801456865052245_ld5.flv?expire=1772665620&sign=c8b621cc008dca6a2e14d9c03929facb"
      },
      "hd": {
        "flv": "https://pull-flv-l77-tt04.tiktokcdn-us.com/stage/stream-1271801456865052245_hd5.flv?expire=1772665620&sign=9116b4b164e0bdf89ce75a5b091aa99f"
      },
      "ao": {
        "flv": "https://pull-flv-l77-tt04.tiktokcdn-us.com/stage/stream-1271801456865052245.flv?expire=1772665620&sign=4b6b9a6477346eb96f69dda01ea81501&only_audio=1"
      }
    }
  },
  {
    "uniqueId": "elizasamiou",
    "nickname": "ΕL1ZA💋S.",
    "avatar": "https://p16-common-sign.tiktokcdn-us.com/tos-maliva-avt-0068/32d88455f6a87fbc48878139093546dc~tplv-tiktokx-cropcenter:1080:1080.webp?dr=9640&refresh_token=5eb1ea6a&x-expires=1771624800&x-signature=3NT69wsdL922suqoC%2FhUCDPZSrY%3D&t=4d5b0474&ps=13740610&shp=a5d48078&shcp=fdd36af4&idc=useast8",
    "live_title": "Happy Vibes 🦄",
    "start_time": 1771444022,
    "start_time_only_time": "21:47:02",
    "status": 2,
    "status_str": "Σε εξέλιξη",
    "stream_urls": {
      "ld": {
        "flv": "https://pull-flv-l77-tt04.tiktokcdn-us.com/stage/stream-1271801100571510357_ld5.flv?expire=1772665627&sign=03abef4cf37f84806faa153dd86a6232"
      },
      "hd": {
        "flv": "https://pull-flv-l77-tt04.tiktokcdn-us.com/stage/stream-1271801100571510357_hd5.flv?expire=1772665627&sign=c82fcc08f27d796736c70a14ff9a45ee"
      },
      "ao": {
        "flv": "https://pull-flv-l77-tt04.tiktokcdn-us.com/stage/stream-1271801100571510357.flv?expire=1772665627&sign=13e787231112059baac53d772c6cc26a&only_audio=1"
      },
      "origin": {
        "flv": "https://pull-flv-l77-tt04.tiktokcdn-us.com/stage/stream-1271801100571510357.flv?expire=1772665627&sign=13e787231112059baac53d772c6cc26a"
      },
      "sd": {
        "flv": "https://pull-flv-l77-tt04.tiktokcdn-us.com/stage/stream-1271801100571510357_zsd5.flv?expire=1772665627&sign=4fa3114b19396ecb7451948e63832f66"
      }
    }
  },
  {
    "uniqueId": "muglikat",
    "nickname": "Katerina MK🐈‍⬛",
    "avatar": "https://p19-common-sign.tiktokcdn-us.com/tos-maliva-avt-0068/7eea4629e4ad164d251372e51a998233~tplv-tiktokx-cropcenter:1080:1080.webp?dr=9640&refresh_token=067af057&x-expires=1771624800&x-signature=avSthQaM8iHQm4n4fKrEbSYR8oU%3D&t=4d5b0474&ps=13740610&shp=a5d48078&shcp=fdd36af4&idc=useast8",
    "live_title": "Καλωσορίσατε🤗￼ ￼￼ Привет 👋",
    "start_time": 1771450874,
    "start_time_only_time": "23:41:14",
    "status": 2,
    "status_str": "Σε εξέλιξη",
    "stream_urls": {
      "ao": {
        "flv": "https://pull-flv-l77-tt04.tiktokcdn-us.com/stage/stream-1271801560401184341.flv?expire=1772665639&sign=674e13ca59f517240b7a324691806942&only_audio=1"
      },
      "origin": {
        "flv": "https://pull-flv-l77-tt04.tiktokcdn-us.com/stage/stream-1271801560401184341.flv?expire=1772665639&sign=674e13ca59f517240b7a324691806942"
      },
      "sd": {
        "flv": "https://pull-flv-l77-tt04.tiktokcdn-us.com/stage/stream-1271801560401184341_zsd5.flv?expire=1772665639&sign=c60504e41709b5844fff03e7488e9a1d"
      },
      "ld": {
        "flv": "https://pull-flv-l77-tt04.tiktokcdn-us.com/stage/stream-1271801560401184341_ld5.flv?expire=1772665639&sign=7079b81e707d8bbeceb7b2c080ca6aa8"
      },
      "hd": {
        "flv": "https://pull-flv-l77-tt04.tiktokcdn-us.com/stage/stream-1271801560401184341_hd5.flv?expire=1772665639&sign=86539b28d210c54ff897096cc02e342d"
      }
    }
  },
  {
    "uniqueId": "mirella_art",
    "nickname": "Mirella Sf 🧸",
    "avatar": "https://p16-common-sign.tiktokcdn-us.com/tos-maliva-avt-0068/bfbf037949fce9c980659715fe9b4ff0~tplv-tiktokx-cropcenter:1080:1080.webp?dr=9640&refresh_token=87a320a8&x-expires=1771628400&x-signature=7GiYOd4rFSwM9d1WfGwQRkU4hbU%3D&t=4d5b0474&ps=13740610&shp=a5d48078&shcp=fdd36af4&idc=useast8",
    "live_title": "Gas na max 🙋🏼‍♀️🎶",
    "start_time": 1771449682,
    "start_time_only_time": "23:21:22",
    "status": 2,
    "status_str": "Σε εξέλιξη",
    "stream_urls": {
      "ld": {
        "flv": "https://pull-flv-l77-tt04.tiktokcdn-us.com/stage/stream-1271801480357086805_ld5.flv?expire=1772665655&sign=5e44f382cac1587f09be4d02819d5d25"
      },
      "hd": {
        "flv": "https://pull-flv-l77-tt04.tiktokcdn-us.com/stage/stream-1271801480357086805_hd5.flv?expire=1772665655&sign=0de640131c6de83b0189cbc02fccee1f"
      },
      "ao": {
        "flv": "https://pull-flv-l77-tt04.tiktokcdn-us.com/stage/stream-1271801480357086805.flv?expire=1772665655&sign=22e9b7d88d5c154a1888bf2889b3454b&only_audio=1"
      },
      "origin": {
        "flv": "https://pull-flv-l77-tt04.tiktokcdn-us.com/stage/stream-1271801480357086805.flv?expire=1772665655&sign=22e9b7d88d5c154a1888bf2889b3454b"
      },
      "sd": {
        "flv": "https://pull-flv-l77-tt04.tiktokcdn-us.com/stage/stream-1271801480357086805_zsd5.flv?expire=1772665655&sign=422e05373b79ff09d0b3e74177da6c35"
      }
    }
  },
  {
    "uniqueId": "evangeloskarevlidis",
    "nickname": "\"Bread & Life\"",
    "avatar": "https://p16-common-sign.tiktokcdn-us.com/tos-maliva-avt-0068/67aca1349be87154ee5464e8b27cad1e~tplv-tiktokx-cropcenter:1080:1080.webp?dr=9640&refresh_token=d531ac88&x-expires=1771624800&x-signature=Vdp6SbuX0Eun9clb%2Bvf2hs5aYmo%3D&t=4d5b0474&ps=13740610&shp=a5d48078&shcp=fdd36af4&idc=useast8",
    "live_title": "",
    "start_time": 1771446847,
    "start_time_only_time": "22:34:07",
    "status": 2,
    "status_str": "Σε εξέλιξη",
    "stream_urls": {
      "ao": {
        "flv": "https://pull-flv-l77-tt04.tiktokcdn-us.com/stage/stream-1271801290111321685.flv?expire=1772665661&sign=604a288796c811c9fe9bd505f85c8013&only_audio=1"
      },
      "origin": {
        "flv": "https://pull-flv-l77-tt04.tiktokcdn-us.com/stage/stream-1271801290111321685.flv?expire=1772665661&sign=604a288796c811c9fe9bd505f85c8013"
      }
    }
  },
  {
    "uniqueId": "thomastsirogiannis2025",
    "nickname": "Θωμάς Στάθης autism💙💙",
    "avatar": "https://p16-common-sign.tiktokcdn-us.com/tos-maliva-avt-0068/09db371434eed2616470ea8b137cc01b~tplv-tiktokx-cropcenter:1080:1080.webp?dr=9640&refresh_token=741166d3&x-expires=1771628400&x-signature=pY0xhglEE%2BYG8%2Bpgj79fAr7eWDA%3D&t=4d5b0474&ps=13740610&shp=a5d48078&shcp=fdd36af4&idc=useast8",
    "live_title": "Η έκπληξη μας",
    "start_time": 1771449375,
    "start_time_only_time": "23:16:15",
    "status": 2,
    "status_str": "Σε εξέλιξη",
    "stream_urls": {
      "sd": {
        "flv": "https://pull-flv-f77-tt04.tiktokcdn-us.com/stage/stream-1271801459756500289_zsd5.flv?expire=1772665663&sign=1751d455f8000d5693fb92421d13b0f9"
      },
      "ld": {
        "flv": "https://pull-flv-f77-tt04.tiktokcdn-us.com/stage/stream-1271801459756500289_ld5.flv?expire=1772665663&sign=2a211d6b4ba3641a1d68fb3d6c7de138"
      },
      "hd": {
        "flv": "https://pull-flv-f77-tt04.tiktokcdn-us.com/stage/stream-1271801459756500289_hd5.flv?expire=1772665663&sign=e9a1ca36e06a74c4755cf7ea49d0562b"
      },
      "ao": {
        "flv": "https://pull-flv-f77-tt04.tiktokcdn-us.com/stage/stream-1271801459756500289.flv?expire=1772665663&sign=0582ae07fee2f75bf5ee24eaebcfb37a&only_audio=1"
      },
      "origin": {
        "flv": "https://pull-flv-f77-tt04.tiktokcdn-us.com/stage/stream-1271801459756500289.flv?expire=1772665663&sign=0582ae07fee2f75bf5ee24eaebcfb37a"
      }
    }
  },
  {
    "uniqueId": "alyskeiaroubini",
    "nickname": "Alyskeia☃️",
    "avatar": "https://p16-common-sign.tiktokcdn-us.com/tos-useast2a-avt-0068-euttp/7323578104226512929~tplv-tiktokx-cropcenter:1080:1080.webp?dr=9640&refresh_token=892f2215&x-expires=1771628400&x-signature=yWABRc0kIF2mN6sJdGsuHBtgaFI%3D&t=4d5b0474&ps=13740610&shp=a5d48078&shcp=fdd36af4&idc=useast8",
    "live_title": "🧸❤️",
    "start_time": 1771451862,
    "start_time_only_time": "23:57:42",
    "status": 2,
    "status_str": "Σε εξέλιξη",
    "stream_urls": {
      "origin": {
        "flv": "https://pull-flv-f77-tt04.tiktokcdn-us.com/stage/stream-1271801626648118593.flv?expire=1772665671&sign=281eb5a18dec6a3267d59313f6921069"
      },
      "sd": {
        "flv": "https://pull-flv-f77-tt04.tiktokcdn-us.com/stage/stream-1271801626648118593_zsd5.flv?expire=1772665671&sign=135b2763b6669e1f4d502305f5a38939"
      },
      "ld": {
        "flv": "https://pull-flv-f77-tt04.tiktokcdn-us.com/stage/stream-1271801626648118593_ld5.flv?expire=1772665671&sign=7ce952c16053ec84244feaf8817222fa"
      },
      "hd": {
        "flv": "https://pull-flv-f77-tt04.tiktokcdn-us.com/stage/stream-1271801626648118593_hd5.flv?expire=1772665671&sign=571e90ea37f78a3899aa322f5fc021d4"
      },
      "ao": {
        "flv": "https://pull-flv-f77-tt04.tiktokcdn-us.com/stage/stream-1271801626648118593.flv?expire=1772665671&sign=281eb5a18dec6a3267d59313f6921069&only_audio=1"
      }
    }
  },
  {
    "uniqueId": "satamoofficial",
    "nickname": "satamoofficial🔥",
    "avatar": "https://p19-common-sign.tiktokcdn-us.com/tos-maliva-avt-0068/5fa3bb1c908e2be44e99f2df23a9b4e3~tplv-tiktokx-cropcenter:1080:1080.webp?dr=9640&refresh_token=ceeb0c51&x-expires=1771624800&x-signature=JZvwhuJeA6bJLPet%2Bsg9yiFurQQ%3D&t=4d5b0474&ps=13740610&shp=a5d48078&shcp=fdd36af4&idc=useast8",
    "live_title": "",
    "start_time": 1771446706,
    "start_time_only_time": "22:31:46",
    "status": 2,
    "status_str": "Σε εξέλιξη",
    "stream_urls": {
      "hd": {
        "flv": "https://pull-flv-l77-tt04.tiktokcdn-us.com/stage/stream-1271801280695633493_hd5.flv?expire=1772665693&sign=c47e2bf186b1d3eb4509a91b9ba2c8a1"
      },
      "ao": {
        "flv": "https://pull-flv-l77-tt04.tiktokcdn-us.com/stage/stream-1271801280695633493.flv?expire=1772665693&sign=dbe91d4d1fe0cbe141ef2c3cf4c78831&only_audio=1"
      },
      "origin": {
        "flv": "https://pull-flv-l77-tt04.tiktokcdn-us.com/stage/stream-1271801280695633493.flv?expire=1772665693&sign=dbe91d4d1fe0cbe141ef2c3cf4c78831"
      },
      "sd": {
        "flv": "https://pull-flv-l77-tt04.tiktokcdn-us.com/stage/stream-1271801280695633493_zsd5.flv?expire=1772665693&sign=3c2a35b1009db0cee8e2d39be7f7a61d"
      },
      "ld": {
        "flv": "https://pull-flv-l77-tt04.tiktokcdn-us.com/stage/stream-1271801280695633493_ld5.flv?expire=1772665693&sign=4b8cd78ed133788cff6f0254232eb606"
      }
    }
  },
  {
    "uniqueId": "petrakosthess",
    "nickname": "ℙℰTℛᎾЅ ℙℰTℛᎯᏦᎾЅ 🎙️94,5 🎭🎧",
    "avatar": "https://p16-common-sign.tiktokcdn-us.com/tos-maliva-avt-0068/2df900b8e56f5a24041b9aed152a3bd8~tplv-tiktokx-cropcenter:1080:1080.webp?dr=9640&refresh_token=3c68c402&x-expires=1771624800&x-signature=wHSv4vgSIfAKyDatpcSg1YTf06o%3D&t=4d5b0474&ps=13740610&shp=a5d48078&shcp=fdd36af4&idc=useast8",
    "live_title": "Petrakos 94,5 FM live show",
    "start_time": 1771452680,
    "start_time_only_time": "00:11:20",
    "status": 2,
    "status_str": "Σε εξέλιξη",
    "stream_urls": {
      "ld": {
        "flv": "https://pull-flv-l77-tt04.tiktokcdn-us.com/stage/stream-1271801681597171285_ld5.flv?expire=1772665703&sign=f34978ad896c90ed4ad3ebe859d36b53"
      },
      "hd": {
        "flv": "https://pull-flv-l77-tt04.tiktokcdn-us.com/stage/stream-1271801681597171285_hd5.flv?expire=1772665703&sign=9756549a0d0b10e030eed3104ebd069d"
      },
      "ao": {
        "flv": "https://pull-flv-l77-tt04.tiktokcdn-us.com/stage/stream-1271801681597171285.flv?expire=1772665703&sign=255aa0367d94c27c9d34904c4d0310a8&only_audio=1"
      },
      "origin": {
        "flv": "https://pull-flv-l77-tt04.tiktokcdn-us.com/stage/stream-1271801681597171285.flv?expire=1772665703&sign=255aa0367d94c27c9d34904c4d0310a8"
      },
      "sd": {
        "flv": "https://pull-flv-l77-tt04.tiktokcdn-us.com/stage/stream-1271801681597171285_zsd5.flv?expire=1772665703&sign=91fa240bef000068db2de7b53313ccb7"
      }
    }
  },
  {
    "uniqueId": "mairi_mihoy_official",
    "nickname": "Μαίρη Μίχου",
    "avatar": "https://p16-common-sign.tiktokcdn-us.com/tos-maliva-avt-0068/be7d7b66146765cf704ba515db8abcd0~tplv-tiktokx-cropcenter:1080:1080.webp?dr=9640&refresh_token=ea2e998c&x-expires=1771628400&x-signature=OOUNhSI0JeEggjNIvc97wFWeAyU%3D&t=4d5b0474&ps=13740610&shp=a5d48078&shcp=fdd36af4&idc=useast8",
    "live_title": "",
    "start_time": 1771452823,
    "start_time_only_time": "00:13:43",
    "status": 2,
    "status_str": "Σε εξέλιξη",
    "stream_urls": {
      "origin": {
        "flv": "https://pull-flv-l77-tt04.tiktokcdn-us.com/stage/stream-1271801691133970005.flv?expire=1772665706&sign=b5c10ff022fcf5e5d8b88a83cddb085d"
      },
      "ao": {
        "flv": "https://pull-flv-l77-tt04.tiktokcdn-us.com/stage/stream-1271801691133970005.flv?expire=1772665706&sign=b5c10ff022fcf5e5d8b88a83cddb085d&only_audio=1"
      }
    }
  },
  {
    "uniqueId": "caesar.el.tio",
    "nickname": "Caesar El Tio",
    "avatar": "https://p16-common-sign.tiktokcdn-us.com/tos-maliva-avt-0068/1f51412ee36e3a29d9d7524ea3385dd4~tplv-tiktokx-cropcenter:1080:1080.webp?dr=9640&refresh_token=de0ef6f3&x-expires=1771624800&x-signature=87yKG1PFKz8CZUoe6KX%2FqAGium0%3D&t=4d5b0474&ps=13740610&shp=a5d48078&shcp=fdd36af4&idc=useast8",
    "live_title": "You know who! 😎",
    "start_time": 1771450812,
    "start_time_only_time": "23:40:12",
    "status": 2,
    "status_str": "Σε εξέλιξη",
    "stream_urls": {
      "origin": {
        "flv": "https://pull-flv-f77-tt04.tiktokcdn-us.com/stage/stream-1271801556238337345.flv?expire=1772665716&sign=0a908f841b7948d17f7e1d4e4056d505"
      },
      "sd": {
        "flv": "https://pull-flv-f77-tt04.tiktokcdn-us.com/stage/stream-1271801556238337345_zsd5.flv?expire=1772665716&sign=8ab41744435cbbe45006a6c684a49e11"
      },
      "ld": {
        "flv": "https://pull-flv-f77-tt04.tiktokcdn-us.com/stage/stream-1271801556238337345_ld5.flv?expire=1772665716&sign=289510e2f2b5d33468e2b35271850933"
      },
      "hd": {
        "flv": "https://pull-flv-f77-tt04.tiktokcdn-us.com/stage/stream-1271801556238337345_hd5.flv?expire=1772665716&sign=812e7e823cd4236434b01722dfe30278"
      },
      "ao": {
        "flv": "https://pull-flv-f77-tt04.tiktokcdn-us.com/stage/stream-1271801556238337345.flv?expire=1772665716&sign=0a908f841b7948d17f7e1d4e4056d505&only_audio=1"
      }
    }
  }
]